[{"bbox": "1 182 444 375", "used": false, "class_name": "diningtable"}, {"bbox": "182 270 357 375", "used": false, "class_name": "chair"}, {"bbox": "340 221 459 375", "used": false, "class_name": "chair"}, {"bbox": "377 182 475 375", "used": false, "class_name": "chair"}, {"bbox": "236 1 310 86", "used": false, "class_name": "tvmonitor"}, {"bbox": "402 114 500 201", "used": false, "class_name": "sofa"}, {"bbox": "104 142 176 214", "used": false, "class_name": "chair"}, {"bbox": "1 152 53 242", "used": false, "class_name": "chair"}, {"bbox": "301 144 376 204", "used": false, "class_name": "chair"}]