[{"bbox": "28 37 477 353", "file_id": "2009_002438", "confidence": "0.9999"}, {"bbox": "135 173 248 268", "file_id": "2010_002708", "confidence": "0.9999"}, {"bbox": "83 158 327 350", "file_id": "2011_005480", "confidence": "0.9999"}, {"bbox": "265 184 407 334", "file_id": "2012_001716", "confidence": "0.9999"}, {"bbox": "141 387 243 486", "file_id": "2012_002336", "confidence": "0.9999"}, {"bbox": "3 183 151 292", "file_id": "2008_001566", "confidence": "0.9998"}, {"bbox": "59 84 463 351", "file_id": "2008_005727", "confidence": "0.9998"}, {"bbox": "49 38 483 323", "file_id": "2008_007915", "confidence": "0.9998"}, {"bbox": "122 77 405 323", "file_id": "2008_008629", "confidence": "0.9998"}, {"bbox": "2 33 473 361", "file_id": "2010_003379", "confidence": "0.9998"}, {"bbox": "24 41 500 319", "file_id": "2011_001138", "confidence": "0.9998"}, {"bbox": "21 40 496 330", "file_id": "2011_001643", "confidence": "0.9998"}, {"bbox": "40 167 181 325", "file_id": "2012_001691", "confidence": "0.9998"}, {"bbox": "200 224 377 332", "file_id": "2012_003631", "confidence": "0.9998"}, {"bbox": "41 92 308 338", "file_id": "2007_003188", "confidence": "0.9997"}, {"bbox": "6 7 494 369", "file_id": "2008_008368", "confidence": "0.9997"}, {"bbox": "-1 0 370 500", "file_id": "2010_001540", "confidence": "0.9997"}, {"bbox": "16 65 464 331", "file_id": "2010_005782", "confidence": "0.9997"}, {"bbox": "211 192 453 325", "file_id": "2010_005848", "confidence": "0.9996"}, {"bbox": "73 220 251 369", "file_id": "2012_001716", "confidence": "0.9996"}, {"bbox": "244 124 471 302", "file_id": "2012_002228", "confidence": "0.9996"}, {"bbox": "54 54 448 316", "file_id": "2009_002371", "confidence": "0.9995"}, {"bbox": "47 9 373 380", "file_id": "2009_004934", "confidence": "0.9995"}, {"bbox": "120 111 360 350", "file_id": "2011_003331", "confidence": "0.9995"}, {"bbox": "125 284 270 453", "file_id": "2007_006581", "confidence": "0.9994"}, {"bbox": "6 -2 441 373", "file_id": "2008_003713", "confidence": "0.9994"}, {"bbox": "270 190 396 285", "file_id": "2008_004040", "confidence": "0.9994"}, {"bbox": "33 45 201 179", "file_id": "2008_008629", "confidence": "0.9994"}, {"bbox": "241 166 349 283", "file_id": "2007_005064", "confidence": "0.9992"}, {"bbox": "3 200 393 416", "file_id": "2009_004444", "confidence": "0.9992"}, {"bbox": "179 211 275 292", "file_id": "2010_006096", "confidence": "0.9991"}, {"bbox": "189 180 259 307", "file_id": "2011_006739", "confidence": "0.9990"}, {"bbox": "365 309 481 375", "file_id": "2012_002112", "confidence": "0.9989"}, {"bbox": "206 139 302 260", "file_id": "2011_006003", "confidence": "0.9988"}, {"bbox": "0 5 362 268", "file_id": "2010_005658", "confidence": "0.9987"}, {"bbox": "17 25 408 243", "file_id": "2009_005156", "confidence": "0.9986"}, {"bbox": "318 179 427 317", "file_id": "2011_006739", "confidence": "0.9986"}, {"bbox": "347 13 456 98", "file_id": "2009_002785", "confidence": "0.9983"}, {"bbox": "0 17 171 142", "file_id": "2009_002785", "confidence": "0.9983"}, {"bbox": "2 -6 493 336", "file_id": "2009_005144", "confidence": "0.9983"}, {"bbox": "88 164 359 473", "file_id": "2011_001028", "confidence": "0.9981"}, {"bbox": "36 130 244 412", "file_id": "2009_001758", "confidence": "0.9976"}, {"bbox": "310 189 418 281", "file_id": "2008_001225", "confidence": "0.9973"}, {"bbox": "224 183 324 277", "file_id": "2008_001225", "confidence": "0.9971"}, {"bbox": "221 192 343 275", "file_id": "2011_001987", "confidence": "0.9970"}, {"bbox": "104 168 291 413", "file_id": "2010_006153", "confidence": "0.9968"}, {"bbox": "5 136 161 245", "file_id": "2012_001919", "confidence": "0.9958"}, {"bbox": "127 182 245 283", "file_id": "2008_001225", "confidence": "0.9953"}, {"bbox": "154 106 293 243", "file_id": "2009_001758", "confidence": "0.9947"}, {"bbox": "269 189 407 413", "file_id": "2011_002281", "confidence": "0.9937"}, {"bbox": "27 288 397 483", "file_id": "2011_006531", "confidence": "0.9929"}, {"bbox": "68 127 244 282", "file_id": "2009_005087", "confidence": "0.9927"}, {"bbox": "2 0 488 280", "file_id": "2010_003350", "confidence": "0.9918"}, {"bbox": "112 216 221 427", "file_id": "2010_006229", "confidence": "0.9916"}, {"bbox": "177 183 287 365", "file_id": "2011_006141", "confidence": "0.9913"}, {"bbox": "0 -14 488 172", "file_id": "2011_001599", "confidence": "0.9905"}, {"bbox": "15 145 191 302", "file_id": "2012_000503", "confidence": "0.9897"}, {"bbox": "20 320 245 470", "file_id": "2007_005368", "confidence": "0.9877"}, {"bbox": "405 168 487 278", "file_id": "2011_006739", "confidence": "0.9860"}, {"bbox": "118 115 465 322", "file_id": "2008_008112", "confidence": "0.9857"}, {"bbox": "141 204 434 315", "file_id": "2012_001919", "confidence": "0.9843"}, {"bbox": "51 342 144 419", "file_id": "2012_001199", "confidence": "0.9842"}, {"bbox": "367 133 479 240", "file_id": "2011_006541", "confidence": "0.9826"}, {"bbox": "73 169 172 243", "file_id": "2012_001281", "confidence": "0.9794"}, {"bbox": "127 231 297 370", "file_id": "2011_001422", "confidence": "0.9791"}, {"bbox": "26 99 270 309", "file_id": "2011_005676", "confidence": "0.9778"}, {"bbox": "22 10 498 272", "file_id": "2011_001441", "confidence": "0.9752"}, {"bbox": "104 126 295 305", "file_id": "2008_006424", "confidence": "0.9746"}, {"bbox": "243 177 442 333", "file_id": "2011_005724", "confidence": "0.9723"}, {"bbox": "11 148 85 224", "file_id": "2012_003986", "confidence": "0.9715"}, {"bbox": "14 150 77 234", "file_id": "2012_001716", "confidence": "0.9700"}, {"bbox": "224 166 403 319", "file_id": "2012_001691", "confidence": "0.9656"}, {"bbox": "48 152 147 229", "file_id": "2011_006739", "confidence": "0.9518"}, {"bbox": "276 276 479 363", "file_id": "2008_007833", "confidence": "0.9418"}, {"bbox": "179 311 244 433", "file_id": "2011_003483", "confidence": "0.9230"}, {"bbox": "3 120 73 230", "file_id": "2010_001246", "confidence": "0.9052"}, {"bbox": "286 163 377 243", "file_id": "2010_001254", "confidence": "0.8940"}, {"bbox": "3 112 70 188", "file_id": "2011_005480", "confidence": "0.8909"}, {"bbox": "437 164 495 219", "file_id": "2012_001330", "confidence": "0.7982"}, {"bbox": "161 166 270 385", "file_id": "2010_000065", "confidence": "0.7661"}, {"bbox": "183 244 221 315", "file_id": "2012_000870", "confidence": "0.7217"}, {"bbox": "35 117 103 199", "file_id": "2011_005480", "confidence": "0.7155"}, {"bbox": "74 259 115 334", "file_id": "2011_006003", "confidence": "0.7073"}, {"bbox": "381 34 473 282", "file_id": "2010_005658", "confidence": "0.6957"}, {"bbox": "321 177 402 227", "file_id": "2012_001330", "confidence": "0.6904"}, {"bbox": "200 190 265 291", "file_id": "2008_004040", "confidence": "0.6833"}, {"bbox": "293 118 472 302", "file_id": "2008_001375", "confidence": "0.6778"}, {"bbox": "123 285 182 365", "file_id": "2012_000870", "confidence": "0.6641"}, {"bbox": "54 155 85 222", "file_id": "2010_006864", "confidence": "0.6580"}, {"bbox": "150 148 179 211", "file_id": "2010_006864", "confidence": "0.6372"}, {"bbox": "197 177 294 286", "file_id": "2012_000516", "confidence": "0.6313"}, {"bbox": "8 143 53 222", "file_id": "2010_001921", "confidence": "0.6109"}, {"bbox": "3 126 92 179", "file_id": "2012_000312", "confidence": "0.5806"}, {"bbox": "0 64 150 230", "file_id": "2009_002785", "confidence": "0.5793"}, {"bbox": "327 308 367 353", "file_id": "2012_001199", "confidence": "0.5766"}, {"bbox": "0 136 63 309", "file_id": "2012_003287", "confidence": "0.5649"}, {"bbox": "419 150 491 253", "file_id": "2011_001538", "confidence": "0.5409"}, {"bbox": "137 140 204 269", "file_id": "2012_001330", "confidence": "0.5059"}, {"bbox": "125 271 155 362", "file_id": "2009_004710", "confidence": "0.4790"}, {"bbox": "433 329 491 370", "file_id": "2012_001649", "confidence": "0.4658"}, {"bbox": "357 174 462 304", "file_id": "2011_006739", "confidence": "0.4556"}, {"bbox": "148 136 325 358", "file_id": "2011_006320", "confidence": "0.4493"}, {"bbox": "265 103 431 216", "file_id": "2012_002105", "confidence": "0.4483"}, {"bbox": "25 154 60 229", "file_id": "2012_001330", "confidence": "0.4435"}, {"bbox": "260 213 375 316", "file_id": "2011_005724", "confidence": "0.3947"}, {"bbox": "230 201 260 255", "file_id": "2008_004113", "confidence": "0.3877"}, {"bbox": "153 333 181 395", "file_id": "2012_001199", "confidence": "0.3834"}, {"bbox": "172 116 280 200", "file_id": "2012_003299", "confidence": "0.3805"}, {"bbox": "25 160 57 227", "file_id": "2010_006864", "confidence": "0.3535"}, {"bbox": "223 262 436 467", "file_id": "2011_006531", "confidence": "0.3476"}, {"bbox": "68 160 282 352", "file_id": "2011_001422", "confidence": "0.3422"}, {"bbox": "0 147 43 231", "file_id": "2010_001246", "confidence": "0.3309"}, {"bbox": "275 248 493 326", "file_id": "2008_001375", "confidence": "0.3245"}, {"bbox": "287 154 396 254", "file_id": "2010_001921", "confidence": "0.3204"}, {"bbox": "81 200 211 413", "file_id": "2011_005605", "confidence": "0.3111"}, {"bbox": "139 173 455 350", "file_id": "2012_003287", "confidence": "0.3007"}, {"bbox": "36 80 64 122", "file_id": "2008_005902", "confidence": "0.2866"}, {"bbox": "175 222 248 313", "file_id": "2012_001716", "confidence": "0.2816"}, {"bbox": "116 187 178 239", "file_id": "2012_001281", "confidence": "0.2815"}, {"bbox": "76 332 229 472", "file_id": "2007_006581", "confidence": "0.2729"}, {"bbox": "363 291 444 366", "file_id": "2008_008368", "confidence": "0.2720"}, {"bbox": "208 154 277 248", "file_id": "2012_001716", "confidence": "0.2690"}, {"bbox": "216 280 249 361", "file_id": "2011_004084", "confidence": "0.2536"}, {"bbox": "200 252 263 362", "file_id": "2011_004084", "confidence": "0.2529"}, {"bbox": "438 216 492 376", "file_id": "2012_001716", "confidence": "0.2422"}, {"bbox": "27 359 150 492", "file_id": "2011_004262", "confidence": "0.2402"}, {"bbox": "273 100 454 357", "file_id": "2010_005658", "confidence": "0.2388"}, {"bbox": "198 51 242 100", "file_id": "2008_005902", "confidence": "0.2291"}, {"bbox": "254 136 288 205", "file_id": "2012_000312", "confidence": "0.2264"}, {"bbox": "4 190 77 272", "file_id": "2008_001566", "confidence": "0.2225"}, {"bbox": "287 325 330 379", "file_id": "2012_002336", "confidence": "0.2181"}, {"bbox": "106 241 178 319", "file_id": "2011_005835", "confidence": "0.2166"}, {"bbox": "58 133 122 212", "file_id": "2011_006739", "confidence": "0.2164"}, {"bbox": "144 110 259 274", "file_id": "2012_001330", "confidence": "0.2135"}, {"bbox": "344 266 379 339", "file_id": "2010_005164", "confidence": "0.2105"}, {"bbox": "370 146 434 228", "file_id": "2011_006541", "confidence": "0.2102"}, {"bbox": "149 247 177 307", "file_id": "2011_004994", "confidence": "0.2082"}, {"bbox": "249 258 405 353", "file_id": "2008_007833", "confidence": "0.2055"}, {"bbox": "72 92 268 289", "file_id": "2009_001758", "confidence": "0.2040"}, {"bbox": "5 132 53 173", "file_id": "2012_000312", "confidence": "0.2023"}, {"bbox": "341 145 496 296", "file_id": "2008_005172", "confidence": "0.2017"}, {"bbox": "274 189 311 253", "file_id": "2008_004113", "confidence": "0.2009"}, {"bbox": "37 69 240 315", "file_id": "2011_005800", "confidence": "0.2009"}, {"bbox": "348 106 447 198", "file_id": "2012_002105", "confidence": "0.1958"}, {"bbox": "308 82 441 313", "file_id": "2008_008629", "confidence": "0.1905"}, {"bbox": "317 164 386 259", "file_id": "2008_001225", "confidence": "0.1822"}, {"bbox": "224 173 273 209", "file_id": "2010_003148", "confidence": "0.1800"}, {"bbox": "385 242 456 458", "file_id": "2011_006531", "confidence": "0.1795"}, {"bbox": "261 91 306 136", "file_id": "2011_005480", "confidence": "0.1763"}, {"bbox": "10 94 95 235", "file_id": "2012_001919", "confidence": "0.1757"}, {"bbox": "134 28 384 316", "file_id": "2009_005144", "confidence": "0.1747"}, {"bbox": "287 184 364 263", "file_id": "2008_001225", "confidence": "0.1721"}, {"bbox": "103 327 172 369", "file_id": "2010_000260", "confidence": "0.1709"}, {"bbox": "338 212 423 290", "file_id": "2008_008511", "confidence": "0.1694"}, {"bbox": "22 110 194 350", "file_id": "2010_006575", "confidence": "0.1690"}, {"bbox": "83 258 116 311", "file_id": "2009_002057", "confidence": "0.1628"}, {"bbox": "126 202 202 273", "file_id": "2008_001225", "confidence": "0.1591"}, {"bbox": "131 56 197 159", "file_id": "2008_008629", "confidence": "0.1545"}, {"bbox": "242 160 328 248", "file_id": "2012_001716", "confidence": "0.1530"}, {"bbox": "88 -5 253 186", "file_id": "2011_001599", "confidence": "0.1529"}, {"bbox": "140 116 268 283", "file_id": "2012_003299", "confidence": "0.1512"}, {"bbox": "294 215 468 354", "file_id": "2012_000516", "confidence": "0.1476"}, {"bbox": "260 239 300 288", "file_id": "2008_002750", "confidence": "0.1441"}, {"bbox": "43 197 428 410", "file_id": "2011_006531", "confidence": "0.1424"}, {"bbox": "83 173 155 232", "file_id": "2011_003190", "confidence": "0.1405"}, {"bbox": "265 210 337 290", "file_id": "2008_004040", "confidence": "0.1398"}, {"bbox": "97 59 289 265", "file_id": "2008_008629", "confidence": "0.1394"}, {"bbox": "433 164 490 265", "file_id": "2012_000510", "confidence": "0.1391"}, {"bbox": "234 161 427 315", "file_id": "2008_001375", "confidence": "0.1356"}, {"bbox": "115 202 198 311", "file_id": "2011_005724", "confidence": "0.1345"}, {"bbox": "67 124 119 202", "file_id": "2011_005480", "confidence": "0.1341"}, {"bbox": "456 170 492 235", "file_id": "2011_006541", "confidence": "0.1339"}, {"bbox": "185 217 312 391", "file_id": "2010_000065", "confidence": "0.1333"}, {"bbox": "322 262 481 327", "file_id": "2012_001691", "confidence": "0.1311"}, {"bbox": "89 171 158 263", "file_id": "2010_002708", "confidence": "0.1309"}, {"bbox": "219 181 288 262", "file_id": "2011_001987", "confidence": "0.1293"}, {"bbox": "235 140 408 265", "file_id": "2012_002322", "confidence": "0.1292"}, {"bbox": "147 317 213 450", "file_id": "2010_006229", "confidence": "0.1275"}, {"bbox": "413 123 460 171", "file_id": "2011_006151", "confidence": "0.1240"}, {"bbox": "195 328 238 369", "file_id": "2012_001649", "confidence": "0.1238"}, {"bbox": "301 163 350 230", "file_id": "2010_001254", "confidence": "0.1205"}, {"bbox": "2 3 68 139", "file_id": "2009_000934", "confidence": "0.1200"}, {"bbox": "256 185 322 279", "file_id": "2012_001716", "confidence": "0.1190"}, {"bbox": "151 136 237 224", "file_id": "2009_001758", "confidence": "0.1180"}, {"bbox": "218 92 261 143", "file_id": "2010_005466", "confidence": "0.1179"}, {"bbox": "315 170 393 271", "file_id": "2011_006739", "confidence": "0.1178"}, {"bbox": "199 74 264 152", "file_id": "2010_005466", "confidence": "0.1175"}, {"bbox": "303 150 424 321", "file_id": "2012_001281", "confidence": "0.1167"}, {"bbox": "11 266 34 330", "file_id": "2011_004994", "confidence": "0.1153"}, {"bbox": "417 315 493 369", "file_id": "2012_002112", "confidence": "0.1140"}, {"bbox": "11 150 54 194", "file_id": "2008_005505", "confidence": "0.1135"}, {"bbox": "282 183 340 268", "file_id": "2012_002995", "confidence": "0.1130"}, {"bbox": "280 248 349 318", "file_id": "2008_005732", "confidence": "0.1129"}, {"bbox": "298 231 377 310", "file_id": "2012_003631", "confidence": "0.1113"}, {"bbox": "92 160 176 265", "file_id": "2012_001691", "confidence": "0.1089"}, {"bbox": "61 195 108 241", "file_id": "2011_003381", "confidence": "0.1052"}, {"bbox": "2 273 79 374", "file_id": "2011_005723", "confidence": "0.1049"}, {"bbox": "328 165 455 314", "file_id": "2012_001691", "confidence": "0.1042"}, {"bbox": "408 78 498 258", "file_id": "2010_005658", "confidence": "0.1011"}, {"bbox": "37 198 82 237", "file_id": "2012_002144", "confidence": "0.0990"}, {"bbox": "104 147 265 328", "file_id": "2011_005800", "confidence": "0.0988"}, {"bbox": "14 97 189 456", "file_id": "2012_002886", "confidence": "0.0978"}, {"bbox": "65 118 167 232", "file_id": "2009_001758", "confidence": "0.0972"}, {"bbox": "42 163 80 221", "file_id": "2012_001330", "confidence": "0.0967"}, {"bbox": "202 413 242 450", "file_id": "2011_000030", "confidence": "0.0948"}, {"bbox": "30 -12 187 175", "file_id": "2011_001599", "confidence": "0.0941"}, {"bbox": "395 190 463 244", "file_id": "2012_001520", "confidence": "0.0936"}, {"bbox": "377 274 469 362", "file_id": "2012_002112", "confidence": "0.0934"}, {"bbox": "115 120 155 203", "file_id": "2011_004277", "confidence": "0.0918"}, {"bbox": "287 125 407 295", "file_id": "2011_006739", "confidence": "0.0914"}, {"bbox": "2 344 162 493", "file_id": "2011_006531", "confidence": "0.0898"}, {"bbox": "22 171 47 235", "file_id": "2012_001330", "confidence": "0.0887"}, {"bbox": "34 130 74 211", "file_id": "2012_001716", "confidence": "0.0886"}, {"bbox": "261 212 335 281", "file_id": "2012_002995", "confidence": "0.0884"}, {"bbox": "391 225 415 275", "file_id": "2012_001882", "confidence": "0.0881"}, {"bbox": "397 308 495 372", "file_id": "2010_003643", "confidence": "0.0867"}, {"bbox": "221 218 289 282", "file_id": "2010_006096", "confidence": "0.0867"}, {"bbox": "410 208 452 416", "file_id": "2011_006531", "confidence": "0.0865"}, {"bbox": "80 244 143 327", "file_id": "2012_003291", "confidence": "0.0852"}, {"bbox": "413 268 492 323", "file_id": "2011_007209", "confidence": "0.0847"}, {"bbox": "27 125 88 217", "file_id": "2010_006864", "confidence": "0.0838"}, {"bbox": "205 124 350 355", "file_id": "2011_001422", "confidence": "0.0832"}, {"bbox": "21 29 68 136", "file_id": "2009_002785", "confidence": "0.0826"}, {"bbox": "411 172 485 271", "file_id": "2012_002995", "confidence": "0.0821"}, {"bbox": "118 139 193 314", "file_id": "2008_006424", "confidence": "0.0820"}, {"bbox": "449 302 487 349", "file_id": "2011_007189", "confidence": "0.0805"}, {"bbox": "4 152 48 226", "file_id": "2012_001716", "confidence": "0.0800"}, {"bbox": "409 300 495 327", "file_id": "2011_007209", "confidence": "0.0794"}, {"bbox": "146 28 212 135", "file_id": "2008_002750", "confidence": "0.0791"}, {"bbox": "228 177 285 211", "file_id": "2008_003313", "confidence": "0.0780"}, {"bbox": "331 313 455 483", "file_id": "2011_006531", "confidence": "0.0771"}, {"bbox": "15 91 155 173", "file_id": "2009_002785", "confidence": "0.0763"}, {"bbox": "325 178 365 220", "file_id": "2012_001330", "confidence": "0.0758"}, {"bbox": "367 247 454 307", "file_id": "2010_001748", "confidence": "0.0756"}, {"bbox": "13 268 73 367", "file_id": "2007_003106", "confidence": "0.0755"}, {"bbox": "251 214 287 294", "file_id": "2008_002750", "confidence": "0.0751"}, {"bbox": "65 283 116 334", "file_id": "2012_004299", "confidence": "0.0749"}, {"bbox": "153 215 227 296", "file_id": "2012_001716", "confidence": "0.0737"}, {"bbox": "97 210 223 453", "file_id": "2007_007892", "confidence": "0.0729"}, {"bbox": "97 298 164 363", "file_id": "2010_000260", "confidence": "0.0729"}, {"bbox": "359 60 422 151", "file_id": "2010_003877", "confidence": "0.0725"}, {"bbox": "75 137 154 228", "file_id": "2011_005480", "confidence": "0.0714"}, {"bbox": "450 297 485 345", "file_id": "2011_001566", "confidence": "0.0710"}, {"bbox": "426 138 490 248", "file_id": "2011_006541", "confidence": "0.0708"}, {"bbox": "42 305 80 383", "file_id": "2008_000785", "confidence": "0.0702"}, {"bbox": "373 234 421 288", "file_id": "2008_008511", "confidence": "0.0702"}, {"bbox": "242 150 315 242", "file_id": "2007_005064", "confidence": "0.0699"}, {"bbox": "51 276 131 351", "file_id": "2012_001649", "confidence": "0.0688"}, {"bbox": "34 163 126 261", "file_id": "2012_001716", "confidence": "0.0683"}, {"bbox": "140 123 215 214", "file_id": "2012_001330", "confidence": "0.0677"}, {"bbox": "66 143 108 188", "file_id": "2011_000203", "confidence": "0.0664"}, {"bbox": "198 291 237 348", "file_id": "2009_002438", "confidence": "0.0656"}, {"bbox": "5 -3 471 349", "file_id": "2009_003944", "confidence": "0.0655"}, {"bbox": "65 28 188 292", "file_id": "2012_000503", "confidence": "0.0655"}, {"bbox": "316 256 373 369", "file_id": "2011_000203", "confidence": "0.0653"}, {"bbox": "446 196 487 247", "file_id": "2011_006541", "confidence": "0.0653"}, {"bbox": "163 152 236 229", "file_id": "2011_005170", "confidence": "0.0648"}, {"bbox": "277 183 400 398", "file_id": "2011_002999", "confidence": "0.0640"}, {"bbox": "51 82 75 116", "file_id": "2008_005902", "confidence": "0.0637"}, {"bbox": "452 163 486 245", "file_id": "2008_002868", "confidence": "0.0636"}, {"bbox": "208 230 285 305", "file_id": "2011_006739", "confidence": "0.0633"}, {"bbox": "3 273 17 336", "file_id": "2011_004994", "confidence": "0.0630"}, {"bbox": "394 83 470 120", "file_id": "2007_009889", "confidence": "0.0629"}, {"bbox": "374 380 459 456", "file_id": "2011_003560", "confidence": "0.0628"}, {"bbox": "178 307 296 481", "file_id": "2007_006581", "confidence": "0.0627"}, {"bbox": "0 247 45 294", "file_id": "2012_001045", "confidence": "0.0622"}, {"bbox": "220 208 305 296", "file_id": "2012_003631", "confidence": "0.0620"}, {"bbox": "78 384 168 488", "file_id": "2011_004262", "confidence": "0.0614"}, {"bbox": "387 182 435 235", "file_id": "2011_004157", "confidence": "0.0613"}, {"bbox": "98 268 117 306", "file_id": "2009_002057", "confidence": "0.0609"}, {"bbox": "122 137 188 222", "file_id": "2008_006424", "confidence": "0.0598"}, {"bbox": "81 129 144 225", "file_id": "2011_006141", "confidence": "0.0596"}, {"bbox": "64 29 152 116", "file_id": "2009_002785", "confidence": "0.0593"}, {"bbox": "0 273 187 326", "file_id": "2008_001375", "confidence": "0.0588"}, {"bbox": "304 -12 462 125", "file_id": "2009_000676", "confidence": "0.0588"}, {"bbox": "26 162 93 239", "file_id": "2012_001330", "confidence": "0.0581"}, {"bbox": "197 313 271 370", "file_id": "2012_001649", "confidence": "0.0576"}, {"bbox": "267 167 341 249", "file_id": "2008_001225", "confidence": "0.0575"}, {"bbox": "85 113 146 209", "file_id": "2009_002785", "confidence": "0.0575"}, {"bbox": "358 130 386 198", "file_id": "2012_000312", "confidence": "0.0569"}, {"bbox": "445 179 493 234", "file_id": "2012_002995", "confidence": "0.0567"}, {"bbox": "202 189 233 294", "file_id": "2011_006739", "confidence": "0.0558"}, {"bbox": "232 183 281 247", "file_id": "2012_001716", "confidence": "0.0558"}, {"bbox": "191 68 263 167", "file_id": "2008_005213", "confidence": "0.0557"}, {"bbox": "148 173 234 257", "file_id": "2009_005087", "confidence": "0.0553"}, {"bbox": "54 139 316 478", "file_id": "2011_007095", "confidence": "0.0553"}, {"bbox": "365 230 434 322", "file_id": "2011_006739", "confidence": "0.0552"}, {"bbox": "80 187 126 230", "file_id": "2011_003190", "confidence": "0.0549"}, {"bbox": "1 103 45 169", "file_id": "2011_005480", "confidence": "0.0549"}, {"bbox": "224 397 253 430", "file_id": "2011_002661", "confidence": "0.0542"}, {"bbox": "281 69 316 112", "file_id": "2011_005371", "confidence": "0.0540"}, {"bbox": "165 -4 232 70", "file_id": "2011_005371", "confidence": "0.0540"}, {"bbox": "96 213 239 383", "file_id": "2009_001758", "confidence": "0.0537"}, {"bbox": "211 72 283 164", "file_id": "2009_001758", "confidence": "0.0537"}, {"bbox": "136 308 171 370", "file_id": "2012_000870", "confidence": "0.0536"}, {"bbox": "206 84 393 306", "file_id": "2012_001281", "confidence": "0.0536"}, {"bbox": "95 179 149 227", "file_id": "2012_001330", "confidence": "0.0536"}, {"bbox": "124 247 192 344", "file_id": "2012_000870", "confidence": "0.0534"}, {"bbox": "215 394 233 429", "file_id": "2011_002661", "confidence": "0.0533"}, {"bbox": "230 172 342 302", "file_id": "2012_003631", "confidence": "0.0532"}, {"bbox": "325 211 395 286", "file_id": "2008_004040", "confidence": "0.0531"}, {"bbox": "340 103 391 163", "file_id": "2008_005933", "confidence": "0.0529"}, {"bbox": "71 233 102 269", "file_id": "2009_001152", "confidence": "0.0529"}, {"bbox": "174 259 261 396", "file_id": "2010_000065", "confidence": "0.0529"}, {"bbox": "34 306 228 472", "file_id": "2011_006531", "confidence": "0.0526"}, {"bbox": "347 203 440 462", "file_id": "2011_006531", "confidence": "0.0522"}, {"bbox": "58 188 465 366", "file_id": "2012_000335", "confidence": "0.0522"}, {"bbox": "165 49 198 104", "file_id": "2008_005902", "confidence": "0.0520"}, {"bbox": "109 209 133 256", "file_id": "2010_006880", "confidence": "0.0515"}, {"bbox": "105 94 164 128", "file_id": "2008_005902", "confidence": "0.0514"}, {"bbox": "423 165 488 298", "file_id": "2007_007016", "confidence": "0.0509"}, {"bbox": "103 246 170 323", "file_id": "2012_003291", "confidence": "0.0508"}, {"bbox": "455 318 486 366", "file_id": "2012_001649", "confidence": "0.0507"}, {"bbox": "150 135 186 249", "file_id": "2012_001330", "confidence": "0.0505"}, {"bbox": "249 179 274 213", "file_id": "2011_004655", "confidence": "0.0503"}, {"bbox": "4 97 47 153", "file_id": "2011_005568", "confidence": "0.0503"}, {"bbox": "267 200 298 285", "file_id": "2008_002750", "confidence": "0.0501"}, {"bbox": "63 114 218 341", "file_id": "2012_001716", "confidence": "0.0501"}, {"bbox": "40 178 78 227", "file_id": "2010_006864", "confidence": "0.0500"}, {"bbox": "342 191 410 221", "file_id": "2012_001330", "confidence": "0.0500"}]